MANIFEST.in
README.txt
setup.py
XStatic_RequireJS.egg-info/PKG-INFO
XStatic_RequireJS.egg-info/SOURCES.txt
XStatic_RequireJS.egg-info/dependency_links.txt
XStatic_RequireJS.egg-info/namespace_packages.txt
XStatic_RequireJS.egg-info/not-zip-safe
XStatic_RequireJS.egg-info/top_level.txt
xstatic/__init__.py
xstatic/pkg/__init__.py
xstatic/pkg/requirejs/__init__.py
xstatic/pkg/requirejs/data/require.js
xstatic/pkg/requirejs/data/require.min.js