Metadata-Version: 1.1
Name: XStatic-RequireJS
Version: 2.1.15.1
Summary: RequireJS 2.1.15 (XStatic packaging standard)
Home-page: http://requirejs.org/
Author: Thomas Kluyver
Author-email: thomas@kluyver.me.uk
License: (same as RequireJS)
Keywords: requirejs xstatic
Platform: any
Classifier: Environment :: Web Environment
Classifier: License :: OSI Approved :: BSD License
Classifier: License :: OSI Approved :: MIT License
Classifier: Programming Language :: JavaScript
